remote_logger/__init__.py
remote_logger/remote_logger_handler.py
remote_logger/clients/__init__.py
remote_logger/clients/logger_client.py
remote_logger/clients/sentry_logger_client.py
remote_logger/clients/stackdriver_logger_client.py
remote_logger/util/__init__.py
remote_logger/util/definitions.py
remote_logger/util/excepts.py
remote_logger-0.3.1.dist-info/LICENSE
remote_logger-0.3.1.dist-info/METADATA
remote_logger-0.3.1.dist-info/WHEEL
remote_logger-0.3.1.dist-info/top_level.txt
remote_logger-0.3.1.dist-info/RECORD
