Metadata-Version: 2.1
Name: remote-logger
Version: 0.3.1
Summary: Remote Logger
Home-page: https://github.com/HenleyKuang/remote-logger
Author: Henley Kuang
Author-email: hekuang@ucdavis.edu
License: GPL
Keywords: python logger
Platform: UNKNOWN
Classifier: Development Status :: 5 - Production/Stable
Classifier: Intended Audience :: Developers
Classifier: License :: OSI Approved :: GNU General Public License v3 (GPLv3)
Classifier: Programming Language :: Python
Classifier: Programming Language :: Python :: 3
Classifier: Programming Language :: Python :: 3.6
Classifier: Programming Language :: Python :: 3.7
Classifier: Topic :: Utilities
Requires-Python: >=3.6
Requires-Dist: google-cloud-logging (==1.12.1)
Requires-Dist: sentry-sdk (==0.10.2)
